{
  "basePath": "../frame_extractor/output",
  "items": [
    {
      "type": "range",
      "prefix": "frame_",
      "start": 1082,
      "end": 1095,
      "digits": 4,
      "extension": ".jpg"
    },
    {
      "type": "range",
      "prefix": "frame_",
      "start": 1097,
      "end": 1109,
      "digits": 4,
      "extension": ".jpg"
    },
    {
      "type": "range",
      "prefix": "frame_",
      "start": 1113,
      "end": 1114,
      "digits": 4,
      "extension": ".jpg"
    },
    {
      "type": "range",
      "prefix": "frame_",
      "start": 1116,
      "end": 1116,
      "digits": 4,
      "extension": ".jpg"
    },
    {
      "type": "range",
      "prefix": "frame_",
      "start": 1742,
      "end": 1742,
      "digits": 4,
      "extension": ".jpg"
    },
    {
      "type": "range",
      "prefix": "frame_",
      "start": 1750,
      "end": 1750,
      "digits": 4,
      "extension": ".jpg"
    },
    {
      "type": "range",
      "prefix": "frame_",
      "start": 1757,
      "end": 1758,
      "digits": 4,
      "extension": ".jpg"
    },
    {
      "type": "range",
      "prefix": "frame_",
      "start": 1760,
      "end": 1760,
      "digits": 4,
      "extension": ".jpg"
    },
    {
      "type": "range",
      "prefix": "frame_",
      "start": 4825,
      "end": 4825,
      "digits": 4,
      "extension": ".jpg"
    },
    {
      "type": "range",
      "prefix": "frame_",
      "start": 4829,
      "end": 4829,
      "digits": 4,
      "extension": ".jpg"
    },
    {
      "type": "range",
      "prefix": "frame_",
      "start": 4833,
      "end": 4833,
      "digits": 4,
      "extension": ".jpg"
    },
    {
      "type": "range",
      "prefix": "frame_",
      "start": 4838,
      "end": 4839,
      "digits": 4,
      "extension": ".jpg"
    }
  ]
}