{
  "basePath": "../frame_extractor/output",
  "items": [
    {
      "type": "range",
      "prefix": "frame_",
      "start": 18,
      "end": 18,
      "digits": 4,
      "extension": ".jpg"
    },
    {
      "type": "range",
      "prefix": "frame_",
      "start": 22,
      "end": 22,
      "digits": 4,
      "extension": ".jpg"
    },
    {
      "type": "range",
      "prefix": "frame_",
      "start": 45,
      "end": 45,
      "digits": 4,
      "extension": ".jpg"
    },
    {
      "type": "range",
      "prefix": "frame_",
      "start": 47,
      "end": 51,
      "digits": 4,
      "extension": ".jpg"
    },
    {
      "type": "range",
      "prefix": "frame_",
      "start": 70,
      "end": 70,
      "digits": 4,
      "extension": ".jpg"
    },
    {
      "type": "range",
      "prefix": "frame_",
      "start": 74,
      "end": 75,
      "digits": 4,
      "extension": ".jpg"
    },
    {
      "type": "range",
      "prefix": "frame_",
      "start": 87,
      "end": 124,
      "digits": 4,
      "extension": ".jpg"
    },
    {
      "type": "range",
      "prefix": "frame_",
      "start": 126,
      "end": 142,
      "digits": 4,
      "extension": ".jpg"
    },
    {
      "type": "range",
      "prefix": "frame_",
      "start": 144,
      "end": 148,
      "digits": 4,
      "extension": ".jpg"
    },
    {
      "type": "range",
      "prefix": "frame_",
      "start": 151,
      "end": 151,
      "digits": 4,
      "extension": ".jpg"
    },
    {
      "type": "range",
      "prefix": "frame_",
      "start": 153,
      "end": 354,
      "digits": 4,
      "extension": ".jpg"
    },
    {
      "type": "range",
      "prefix": "frame_",
      "start": 358,
      "end": 358,
      "digits": 4,
      "extension": ".jpg"
    },
    {
      "type": "range",
      "prefix": "frame_",
      "start": 370,
      "end": 370,
      "digits": 4,
      "extension": ".jpg"
    },
    {
      "type": "range",
      "prefix": "frame_",
      "start": 385,
      "end": 385,
      "digits": 4,
      "extension": ".jpg"
    },
    {
      "type": "range",
      "prefix": "frame_",
      "start": 388,
      "end": 389,
      "digits": 4,
      "extension": ".jpg"
    },
    {
      "type": "range",
      "prefix": "frame_",
      "start": 394,
      "end": 396,
      "digits": 4,
      "extension": ".jpg"
    },
    {
      "type": "range",
      "prefix": "frame_",
      "start": 398,
      "end": 398,
      "digits": 4,
      "extension": ".jpg"
    },
    {
      "type": "range",
      "prefix": "frame_",
      "start": 401,
      "end": 504,
      "digits": 4,
      "extension": ".jpg"
    },
    {
      "type": "range",
      "prefix": "frame_",
      "start": 506,
      "end": 576,
      "digits": 4,
      "extension": ".jpg"
    },
    {
      "type": "range",
      "prefix": "frame_",
      "start": 578,
      "end": 811,
      "digits": 4,
      "extension": ".jpg"
    },
    {
      "type": "range",
      "prefix": "frame_",
      "start": 813,
      "end": 872,
      "digits": 4,
      "extension": ".jpg"
    },
    {
      "type": "range",
      "prefix": "frame_",
      "start": 877,
      "end": 877,
      "digits": 4,
      "extension": ".jpg"
    },
    {
      "type": "range",
      "prefix": "frame_",
      "start": 880,
      "end": 880,
      "digits": 4,
      "extension": ".jpg"
    },
    {
      "type": "range",
      "prefix": "frame_",
      "start": 887,
      "end": 887,
      "digits": 4,
      "extension": ".jpg"
    },
    {
      "type": "range",
      "prefix": "frame_",
      "start": 889,
      "end": 889,
      "digits": 4,
      "extension": ".jpg"
    },
    {
      "type": "range",
      "prefix": "frame_",
      "start": 907,
      "end": 921,
      "digits": 4,
      "extension": ".jpg"
    },
    {
      "type": "range",
      "prefix": "frame_",
      "start": 925,
      "end": 926,
      "digits": 4,
      "extension": ".jpg"
    },
    {
      "type": "range",
      "prefix": "frame_",
      "start": 929,
      "end": 931,
      "digits": 4,
      "extension": ".jpg"
    },
    {
      "type": "range",
      "prefix": "frame_",
      "start": 934,
      "end": 935,
      "digits": 4,
      "extension": ".jpg"
    },
    {
      "type": "range",
      "prefix": "frame_",
      "start": 937,
      "end": 939,
      "digits": 4,
      "extension": ".jpg"
    },
    {
      "type": "range",
      "prefix": "frame_",
      "start": 942,
      "end": 943,
      "digits": 4,
      "extension": ".jpg"
    },
    {
      "type": "range",
      "prefix": "frame_",
      "start": 947,
      "end": 947,
      "digits": 4,
      "extension": ".jpg"
    },
    {
      "type": "range",
      "prefix": "frame_",
      "start": 951,
      "end": 961,
      "digits": 4,
      "extension": ".jpg"
    },
    {
      "type": "range",
      "prefix": "frame_",
      "start": 963,
      "end": 1042,
      "digits": 4,
      "extension": ".jpg"
    },
    {
      "type": "range",
      "prefix": "frame_",
      "start": 1048,
      "end": 1048,
      "digits": 4,
      "extension": ".jpg"
    },
    {
      "type": "range",
      "prefix": "frame_",
      "start": 1055,
      "end": 1170,
      "digits": 4,
      "extension": ".jpg"
    },
    {
      "type": "range",
      "prefix": "frame_",
      "start": 1173,
      "end": 1174,
      "digits": 4,
      "extension": ".jpg"
    },
    {
      "type": "range",
      "prefix": "frame_",
      "start": 1177,
      "end": 1286,
      "digits": 4,
      "extension": ".jpg"
    },
    {
      "type": "range",
      "prefix": "frame_",
      "start": 1290,
      "end": 1290,
      "digits": 4,
      "extension": ".jpg"
    },
    {
      "type": "range",
      "prefix": "frame_",
      "start": 1292,
      "end": 1331,
      "digits": 4,
      "extension": ".jpg"
    },
    {
      "type": "range",
      "prefix": "frame_",
      "start": 1333,
      "end": 1434,
      "digits": 4,
      "extension": ".jpg"
    },
    {
      "type": "range",
      "prefix": "frame_",
      "start": 1436,
      "end": 1442,
      "digits": 4,
      "extension": ".jpg"
    },
    {
      "type": "range",
      "prefix": "frame_",
      "start": 1444,
      "end": 1444,
      "digits": 4,
      "extension": ".jpg"
    },
    {
      "type": "range",
      "prefix": "frame_",
      "start": 1454,
      "end": 1457,
      "digits": 4,
      "extension": ".jpg"
    },
    {
      "type": "range",
      "prefix": "frame_",
      "start": 1462,
      "end": 1587,
      "digits": 4,
      "extension": ".jpg"
    },
    {
      "type": "range",
      "prefix": "frame_",
      "start": 1594,
      "end": 1659,
      "digits": 4,
      "extension": ".jpg"
    },
    {
      "type": "range",
      "prefix": "frame_",
      "start": 1668,
      "end": 1847,
      "digits": 4,
      "extension": ".jpg"
    },
    {
      "type": "range",
      "prefix": "frame_",
      "start": 1849,
      "end": 1896,
      "digits": 4,
      "extension": ".jpg"
    },
    {
      "type": "range",
      "prefix": "frame_",
      "start": 1898,
      "end": 1898,
      "digits": 4,
      "extension": ".jpg"
    },
    {
      "type": "range",
      "prefix": "frame_",
      "start": 1904,
      "end": 1917,
      "digits": 4,
      "extension": ".jpg"
    },
    {
      "type": "range",
      "prefix": "frame_",
      "start": 1929,
      "end": 2035,
      "digits": 4,
      "extension": ".jpg"
    },
    {
      "type": "range",
      "prefix": "frame_",
      "start": 2037,
      "end": 2037,
      "digits": 4,
      "extension": ".jpg"
    },
    {
      "type": "range",
      "prefix": "frame_",
      "start": 2039,
      "end": 2040,
      "digits": 4,
      "extension": ".jpg"
    },
    {
      "type": "range",
      "prefix": "frame_",
      "start": 2045,
      "end": 2046,
      "digits": 4,
      "extension": ".jpg"
    },
    {
      "type": "range",
      "prefix": "frame_",
      "start": 2052,
      "end": 2055,
      "digits": 4,
      "extension": ".jpg"
    },
    {
      "type": "range",
      "prefix": "frame_",
      "start": 2057,
      "end": 2081,
      "digits": 4,
      "extension": ".jpg"
    },
    {
      "type": "range",
      "prefix": "frame_",
      "start": 2087,
      "end": 2119,
      "digits": 4,
      "extension": ".jpg"
    },
    {
      "type": "range",
      "prefix": "frame_",
      "start": 2121,
      "end": 2121,
      "digits": 4,
      "extension": ".jpg"
    },
    {
      "type": "range",
      "prefix": "frame_",
      "start": 2123,
      "end": 2157,
      "digits": 4,
      "extension": ".jpg"
    },
    {
      "type": "range",
      "prefix": "frame_",
      "start": 2159,
      "end": 2175,
      "digits": 4,
      "extension": ".jpg"
    },
    {
      "type": "range",
      "prefix": "frame_",
      "start": 2178,
      "end": 2237,
      "digits": 4,
      "extension": ".jpg"
    },
    {
      "type": "range",
      "prefix": "frame_",
      "start": 2239,
      "end": 2239,
      "digits": 4,
      "extension": ".jpg"
    },
    {
      "type": "range",
      "prefix": "frame_",
      "start": 2241,
      "end": 2244,
      "digits": 4,
      "extension": ".jpg"
    },
    {
      "type": "range",
      "prefix": "frame_",
      "start": 2247,
      "end": 2315,
      "digits": 4,
      "extension": ".jpg"
    },
    {
      "type": "range",
      "prefix": "frame_",
      "start": 2317,
      "end": 2317,
      "digits": 4,
      "extension": ".jpg"
    },
    {
      "type": "range",
      "prefix": "frame_",
      "start": 2324,
      "end": 2328,
      "digits": 4,
      "extension": ".jpg"
    },
    {
      "type": "range",
      "prefix": "frame_",
      "start": 2330,
      "end": 2330,
      "digits": 4,
      "extension": ".jpg"
    },
    {
      "type": "range",
      "prefix": "frame_",
      "start": 2333,
      "end": 2394,
      "digits": 4,
      "extension": ".jpg"
    },
    {
      "type": "range",
      "prefix": "frame_",
      "start": 2401,
      "end": 2405,
      "digits": 4,
      "extension": ".jpg"
    },
    {
      "type": "range",
      "prefix": "frame_",
      "start": 2407,
      "end": 2410,
      "digits": 4,
      "extension": ".jpg"
    },
    {
      "type": "range",
      "prefix": "frame_",
      "start": 2412,
      "end": 2412,
      "digits": 4,
      "extension": ".jpg"
    },
    {
      "type": "range",
      "prefix": "frame_",
      "start": 2415,
      "end": 2416,
      "digits": 4,
      "extension": ".jpg"
    },
    {
      "type": "range",
      "prefix": "frame_",
      "start": 2418,
      "end": 2585,
      "digits": 4,
      "extension": ".jpg"
    },
    {
      "type": "range",
      "prefix": "frame_",
      "start": 2587,
      "end": 2609,
      "digits": 4,
      "extension": ".jpg"
    },
    {
      "type": "range",
      "prefix": "frame_",
      "start": 2611,
      "end": 2612,
      "digits": 4,
      "extension": ".jpg"
    },
    {
      "type": "range",
      "prefix": "frame_",
      "start": 2614,
      "end": 2616,
      "digits": 4,
      "extension": ".jpg"
    },
    {
      "type": "range",
      "prefix": "frame_",
      "start": 2618,
      "end": 2695,
      "digits": 4,
      "extension": ".jpg"
    },
    {
      "type": "range",
      "prefix": "frame_",
      "start": 2699,
      "end": 2803,
      "digits": 4,
      "extension": ".jpg"
    },
    {
      "type": "range",
      "prefix": "frame_",
      "start": 2805,
      "end": 2914,
      "digits": 4,
      "extension": ".jpg"
    },
    {
      "type": "range",
      "prefix": "frame_",
      "start": 2916,
      "end": 2922,
      "digits": 4,
      "extension": ".jpg"
    },
    {
      "type": "range",
      "prefix": "frame_",
      "start": 2924,
      "end": 2937,
      "digits": 4,
      "extension": ".jpg"
    },
    {
      "type": "range",
      "prefix": "frame_",
      "start": 2942,
      "end": 2942,
      "digits": 4,
      "extension": ".jpg"
    },
    {
      "type": "range",
      "prefix": "frame_",
      "start": 2948,
      "end": 3038,
      "digits": 4,
      "extension": ".jpg"
    },
    {
      "type": "range",
      "prefix": "frame_",
      "start": 3041,
      "end": 3080,
      "digits": 4,
      "extension": ".jpg"
    },
    {
      "type": "range",
      "prefix": "frame_",
      "start": 3087,
      "end": 3098,
      "digits": 4,
      "extension": ".jpg"
    },
    {
      "type": "range",
      "prefix": "frame_",
      "start": 3102,
      "end": 3122,
      "digits": 4,
      "extension": ".jpg"
    },
    {
      "type": "range",
      "prefix": "frame_",
      "start": 3124,
      "end": 3125,
      "digits": 4,
      "extension": ".jpg"
    },
    {
      "type": "range",
      "prefix": "frame_",
      "start": 3129,
      "end": 3175,
      "digits": 4,
      "extension": ".jpg"
    },
    {
      "type": "range",
      "prefix": "frame_",
      "start": 3181,
      "end": 3181,
      "digits": 4,
      "extension": ".jpg"
    },
    {
      "type": "range",
      "prefix": "frame_",
      "start": 3184,
      "end": 3184,
      "digits": 4,
      "extension": ".jpg"
    },
    {
      "type": "range",
      "prefix": "frame_",
      "start": 3186,
      "end": 3188,
      "digits": 4,
      "extension": ".jpg"
    },
    {
      "type": "range",
      "prefix": "frame_",
      "start": 3191,
      "end": 3192,
      "digits": 4,
      "extension": ".jpg"
    },
    {
      "type": "range",
      "prefix": "frame_",
      "start": 3195,
      "end": 3341,
      "digits": 4,
      "extension": ".jpg"
    },
    {
      "type": "range",
      "prefix": "frame_",
      "start": 3345,
      "end": 3350,
      "digits": 4,
      "extension": ".jpg"
    },
    {
      "type": "range",
      "prefix": "frame_",
      "start": 3352,
      "end": 3352,
      "digits": 4,
      "extension": ".jpg"
    },
    {
      "type": "range",
      "prefix": "frame_",
      "start": 3357,
      "end": 3373,
      "digits": 4,
      "extension": ".jpg"
    },
    {
      "type": "range",
      "prefix": "frame_",
      "start": 3379,
      "end": 3379,
      "digits": 4,
      "extension": ".jpg"
    },
    {
      "type": "range",
      "prefix": "frame_",
      "start": 3385,
      "end": 3388,
      "digits": 4,
      "extension": ".jpg"
    },
    {
      "type": "range",
      "prefix": "frame_",
      "start": 3394,
      "end": 3430,
      "digits": 4,
      "extension": ".jpg"
    },
    {
      "type": "range",
      "prefix": "frame_",
      "start": 3433,
      "end": 3473,
      "digits": 4,
      "extension": ".jpg"
    },
    {
      "type": "range",
      "prefix": "frame_",
      "start": 3475,
      "end": 3527,
      "digits": 4,
      "extension": ".jpg"
    },
    {
      "type": "range",
      "prefix": "frame_",
      "start": 3529,
      "end": 3570,
      "digits": 4,
      "extension": ".jpg"
    },
    {
      "type": "range",
      "prefix": "frame_",
      "start": 3583,
      "end": 3583,
      "digits": 4,
      "extension": ".jpg"
    },
    {
      "type": "range",
      "prefix": "frame_",
      "start": 3588,
      "end": 3611,
      "digits": 4,
      "extension": ".jpg"
    },
    {
      "type": "range",
      "prefix": "frame_",
      "start": 3613,
      "end": 3613,
      "digits": 4,
      "extension": ".jpg"
    },
    {
      "type": "range",
      "prefix": "frame_",
      "start": 3616,
      "end": 3616,
      "digits": 4,
      "extension": ".jpg"
    },
    {
      "type": "range",
      "prefix": "frame_",
      "start": 3618,
      "end": 3619,
      "digits": 4,
      "extension": ".jpg"
    },
    {
      "type": "range",
      "prefix": "frame_",
      "start": 3621,
      "end": 3622,
      "digits": 4,
      "extension": ".jpg"
    },
    {
      "type": "range",
      "prefix": "frame_",
      "start": 3624,
      "end": 3625,
      "digits": 4,
      "extension": ".jpg"
    },
    {
      "type": "range",
      "prefix": "frame_",
      "start": 3627,
      "end": 3629,
      "digits": 4,
      "extension": ".jpg"
    },
    {
      "type": "range",
      "prefix": "frame_",
      "start": 3633,
      "end": 3633,
      "digits": 4,
      "extension": ".jpg"
    },
    {
      "type": "range",
      "prefix": "frame_",
      "start": 3635,
      "end": 3636,
      "digits": 4,
      "extension": ".jpg"
    },
    {
      "type": "range",
      "prefix": "frame_",
      "start": 3639,
      "end": 3640,
      "digits": 4,
      "extension": ".jpg"
    },
    {
      "type": "range",
      "prefix": "frame_",
      "start": 3643,
      "end": 3645,
      "digits": 4,
      "extension": ".jpg"
    },
    {
      "type": "range",
      "prefix": "frame_",
      "start": 3649,
      "end": 3649,
      "digits": 4,
      "extension": ".jpg"
    },
    {
      "type": "range",
      "prefix": "frame_",
      "start": 3651,
      "end": 3663,
      "digits": 4,
      "extension": ".jpg"
    },
    {
      "type": "range",
      "prefix": "frame_",
      "start": 3665,
      "end": 3665,
      "digits": 4,
      "extension": ".jpg"
    },
    {
      "type": "range",
      "prefix": "frame_",
      "start": 3669,
      "end": 3669,
      "digits": 4,
      "extension": ".jpg"
    },
    {
      "type": "range",
      "prefix": "frame_",
      "start": 3671,
      "end": 3695,
      "digits": 4,
      "extension": ".jpg"
    },
    {
      "type": "range",
      "prefix": "frame_",
      "start": 3697,
      "end": 3733,
      "digits": 4,
      "extension": ".jpg"
    },
    {
      "type": "range",
      "prefix": "frame_",
      "start": 3735,
      "end": 3744,
      "digits": 4,
      "extension": ".jpg"
    },
    {
      "type": "range",
      "prefix": "frame_",
      "start": 3746,
      "end": 3758,
      "digits": 4,
      "extension": ".jpg"
    },
    {
      "type": "range",
      "prefix": "frame_",
      "start": 3760,
      "end": 3762,
      "digits": 4,
      "extension": ".jpg"
    },
    {
      "type": "range",
      "prefix": "frame_",
      "start": 3764,
      "end": 3764,
      "digits": 4,
      "extension": ".jpg"
    },
    {
      "type": "range",
      "prefix": "frame_",
      "start": 3766,
      "end": 3813,
      "digits": 4,
      "extension": ".jpg"
    },
    {
      "type": "range",
      "prefix": "frame_",
      "start": 3816,
      "end": 3816,
      "digits": 4,
      "extension": ".jpg"
    },
    {
      "type": "range",
      "prefix": "frame_",
      "start": 3818,
      "end": 3820,
      "digits": 4,
      "extension": ".jpg"
    },
    {
      "type": "range",
      "prefix": "frame_",
      "start": 3822,
      "end": 3823,
      "digits": 4,
      "extension": ".jpg"
    },
    {
      "type": "range",
      "prefix": "frame_",
      "start": 3825,
      "end": 3826,
      "digits": 4,
      "extension": ".jpg"
    },
    {
      "type": "range",
      "prefix": "frame_",
      "start": 3833,
      "end": 3833,
      "digits": 4,
      "extension": ".jpg"
    },
    {
      "type": "range",
      "prefix": "frame_",
      "start": 3835,
      "end": 3843,
      "digits": 4,
      "extension": ".jpg"
    },
    {
      "type": "range",
      "prefix": "frame_",
      "start": 3847,
      "end": 3847,
      "digits": 4,
      "extension": ".jpg"
    },
    {
      "type": "range",
      "prefix": "frame_",
      "start": 3853,
      "end": 3870,
      "digits": 4,
      "extension": ".jpg"
    },
    {
      "type": "range",
      "prefix": "frame_",
      "start": 3877,
      "end": 3880,
      "digits": 4,
      "extension": ".jpg"
    },
    {
      "type": "range",
      "prefix": "frame_",
      "start": 3890,
      "end": 3919,
      "digits": 4,
      "extension": ".jpg"
    },
    {
      "type": "range",
      "prefix": "frame_",
      "start": 3921,
      "end": 3940,
      "digits": 4,
      "extension": ".jpg"
    },
    {
      "type": "range",
      "prefix": "frame_",
      "start": 3959,
      "end": 4010,
      "digits": 4,
      "extension": ".jpg"
    },
    {
      "type": "range",
      "prefix": "frame_",
      "start": 4016,
      "end": 4016,
      "digits": 4,
      "extension": ".jpg"
    },
    {
      "type": "range",
      "prefix": "frame_",
      "start": 4018,
      "end": 4018,
      "digits": 4,
      "extension": ".jpg"
    },
    {
      "type": "range",
      "prefix": "frame_",
      "start": 4020,
      "end": 4020,
      "digits": 4,
      "extension": ".jpg"
    },
    {
      "type": "range",
      "prefix": "frame_",
      "start": 4026,
      "end": 4033,
      "digits": 4,
      "extension": ".jpg"
    },
    {
      "type": "range",
      "prefix": "frame_",
      "start": 4035,
      "end": 4035,
      "digits": 4,
      "extension": ".jpg"
    },
    {
      "type": "range",
      "prefix": "frame_",
      "start": 4039,
      "end": 4047,
      "digits": 4,
      "extension": ".jpg"
    },
    {
      "type": "range",
      "prefix": "frame_",
      "start": 4049,
      "end": 4052,
      "digits": 4,
      "extension": ".jpg"
    },
    {
      "type": "range",
      "prefix": "frame_",
      "start": 4054,
      "end": 4084,
      "digits": 4,
      "extension": ".jpg"
    },
    {
      "type": "range",
      "prefix": "frame_",
      "start": 4090,
      "end": 4144,
      "digits": 4,
      "extension": ".jpg"
    },
    {
      "type": "range",
      "prefix": "frame_",
      "start": 4152,
      "end": 4153,
      "digits": 4,
      "extension": ".jpg"
    },
    {
      "type": "range",
      "prefix": "frame_",
      "start": 4157,
      "end": 4171,
      "digits": 4,
      "extension": ".jpg"
    },
    {
      "type": "range",
      "prefix": "frame_",
      "start": 4173,
      "end": 4206,
      "digits": 4,
      "extension": ".jpg"
    },
    {
      "type": "range",
      "prefix": "frame_",
      "start": 4208,
      "end": 4216,
      "digits": 4,
      "extension": ".jpg"
    },
    {
      "type": "range",
      "prefix": "frame_",
      "start": 4218,
      "end": 4229,
      "digits": 4,
      "extension": ".jpg"
    },
    {
      "type": "range",
      "prefix": "frame_",
      "start": 4231,
      "end": 4237,
      "digits": 4,
      "extension": ".jpg"
    },
    {
      "type": "range",
      "prefix": "frame_",
      "start": 4246,
      "end": 4253,
      "digits": 4,
      "extension": ".jpg"
    },
    {
      "type": "range",
      "prefix": "frame_",
      "start": 4256,
      "end": 4256,
      "digits": 4,
      "extension": ".jpg"
    },
    {
      "type": "range",
      "prefix": "frame_",
      "start": 4263,
      "end": 4263,
      "digits": 4,
      "extension": ".jpg"
    },
    {
      "type": "range",
      "prefix": "frame_",
      "start": 4267,
      "end": 4267,
      "digits": 4,
      "extension": ".jpg"
    },
    {
      "type": "range",
      "prefix": "frame_",
      "start": 4269,
      "end": 4283,
      "digits": 4,
      "extension": ".jpg"
    },
    {
      "type": "range",
      "prefix": "frame_",
      "start": 4286,
      "end": 4288,
      "digits": 4,
      "extension": ".jpg"
    },
    {
      "type": "range",
      "prefix": "frame_",
      "start": 4290,
      "end": 4290,
      "digits": 4,
      "extension": ".jpg"
    },
    {
      "type": "range",
      "prefix": "frame_",
      "start": 4293,
      "end": 4330,
      "digits": 4,
      "extension": ".jpg"
    },
    {
      "type": "range",
      "prefix": "frame_",
      "start": 4332,
      "end": 4333,
      "digits": 4,
      "extension": ".jpg"
    },
    {
      "type": "range",
      "prefix": "frame_",
      "start": 4336,
      "end": 4336,
      "digits": 4,
      "extension": ".jpg"
    },
    {
      "type": "range",
      "prefix": "frame_",
      "start": 4338,
      "end": 4338,
      "digits": 4,
      "extension": ".jpg"
    },
    {
      "type": "range",
      "prefix": "frame_",
      "start": 4345,
      "end": 4345,
      "digits": 4,
      "extension": ".jpg"
    },
    {
      "type": "range",
      "prefix": "frame_",
      "start": 4348,
      "end": 4367,
      "digits": 4,
      "extension": ".jpg"
    },
    {
      "type": "range",
      "prefix": "frame_",
      "start": 4369,
      "end": 4378,
      "digits": 4,
      "extension": ".jpg"
    },
    {
      "type": "range",
      "prefix": "frame_",
      "start": 4407,
      "end": 4407,
      "digits": 4,
      "extension": ".jpg"
    },
    {
      "type": "range",
      "prefix": "frame_",
      "start": 4409,
      "end": 4409,
      "digits": 4,
      "extension": ".jpg"
    },
    {
      "type": "range",
      "prefix": "frame_",
      "start": 4411,
      "end": 4627,
      "digits": 4,
      "extension": ".jpg"
    },
    {
      "type": "range",
      "prefix": "frame_",
      "start": 4633,
      "end": 4657,
      "digits": 4,
      "extension": ".jpg"
    },
    {
      "type": "range",
      "prefix": "frame_",
      "start": 4659,
      "end": 4666,
      "digits": 4,
      "extension": ".jpg"
    },
    {
      "type": "range",
      "prefix": "frame_",
      "start": 4668,
      "end": 4678,
      "digits": 4,
      "extension": ".jpg"
    },
    {
      "type": "range",
      "prefix": "frame_",
      "start": 4685,
      "end": 4691,
      "digits": 4,
      "extension": ".jpg"
    },
    {
      "type": "range",
      "prefix": "frame_",
      "start": 4693,
      "end": 4707,
      "digits": 4,
      "extension": ".jpg"
    },
    {
      "type": "range",
      "prefix": "frame_",
      "start": 4709,
      "end": 4711,
      "digits": 4,
      "extension": ".jpg"
    },
    {
      "type": "range",
      "prefix": "frame_",
      "start": 4713,
      "end": 4714,
      "digits": 4,
      "extension": ".jpg"
    },
    {
      "type": "range",
      "prefix": "frame_",
      "start": 4718,
      "end": 4860,
      "digits": 4,
      "extension": ".jpg"
    },
    {
      "type": "range",
      "prefix": "frame_",
      "start": 4868,
      "end": 4874,
      "digits": 4,
      "extension": ".jpg"
    },
    {
      "type": "range",
      "prefix": "frame_",
      "start": 4877,
      "end": 4877,
      "digits": 4,
      "extension": ".jpg"
    },
    {
      "type": "range",
      "prefix": "frame_",
      "start": 4883,
      "end": 4891,
      "digits": 4,
      "extension": ".jpg"
    },
    {
      "type": "range",
      "prefix": "frame_",
      "start": 4893,
      "end": 5081,
      "digits": 4,
      "extension": ".jpg"
    },
    {
      "type": "range",
      "prefix": "frame_",
      "start": 5083,
      "end": 5127,
      "digits": 4,
      "extension": ".jpg"
    },
    {
      "type": "range",
      "prefix": "frame_",
      "start": 5130,
      "end": 5142,
      "digits": 4,
      "extension": ".jpg"
    },
    {
      "type": "range",
      "prefix": "frame_",
      "start": 5144,
      "end": 5199,
      "digits": 4,
      "extension": ".jpg"
    }
  ]
}